{
  "name": "2fauth",
  "slug": "2fauth",
  "tagline": "A self-hosted web application for managing and generating multi-device two-factor auth codes",
  "description": "2FAuth is an open-source, self-hosted web application built to manage your two-factor authentication (2FA) accounts and generate their security codes (TOTP/HOTP and Steam Guard). It supports features like adding accounts via QR code or manually, organising accounts into groups, encryption of sensitive data, auto-logout on inactivity, and single-user usage. It's designed for both mobile and desktop access, giving you an alternative to smartphone-only apps like Google Authenticator—so you can run 2FAuth on your own server, backup your database, and avoid relying solely on a mobile device.",
  "categories": [
    2
  ],
  "metadata": {
    "sponsored": false,
    "license": "AGPL-3.0",
    "version": "v5.6.1",
    "date_app_added": "2025-11-23",
    "date_last_released": "2025-11-21",
    "date_last_commit": "2025-12-20",
    "github_stars": 3634,
    "github_contributors": 17,
    "github_commits_this_year": 84,
    "github_issues_open": 41,
    "github_issues_closed_this_year": 47,
    "github_releases_this_year": 5
  },
  "resources": {
    "website": "https://docs.2fauth.app",
    "documentation": "https://github.com/Bubka/2FAuth",
    "source_code": "https://github.com/Bubka/2FAuth",
    "logo": "/icons/2fauth.webp",
    "screenshot": "/uploads/2fauth.png",
    "issues": "https://github.com/Bubka/2FAuth/issues",
    "releases": "https://github.com/Bubka/2FAuth/releases",
    "logo_light": "/icons/2fauth-light.webp"
  },
  "features": [
    {
      "title": "Two-Factor Authentication",
      "description": "Generate TOTP/HOTP and Steam Guard security codes for your accounts"
    },
    {
      "title": "QR Code Generation",
      "description": "Add accounts via QR code scanning or manual entry"
    },
    {
      "title": "Folder Organization",
      "description": "Organize your 2FA accounts into custom groups for better management"
    },
    {
      "title": "End-to-End Encryption",
      "description": "Sensitive data is encrypted to keep your accounts secure"
    },
    {
      "title": "Self-Hosted",
      "description": "Run on your own server with full control over your data"
    },
    {
      "title": "Multi-Device Sync",
      "description": "Access your 2FA codes from mobile and desktop devices"
    },
    {
      "title": "Database Backup",
      "description": "Backup your database to prevent losing your 2FA accounts"
    },
    {
      "title": "Session Management",
      "description": "Automatic logout on inactivity for enhanced security"
    }
  ],
  "platform_support": {
    "desktop": {
      "linux": true,
      "windows": true,
      "macos": true
    },
    "mobile": {
      "android": true,
      "ios": true
    },
    "web_app": true,
    "browser_extension": true,
    "cli_only": true
  },
  "hosting_options": {
    "self_hosted": true,
    "managed_cloud": true,
    "saas": false
  },
  "interfaces": {
    "cli": true,
    "gui": true,
    "web_ui": true,
    "api": true,
    "tui": true
  },
  "deployment_methods": {
    "script": true,
    "docker": true,
    "docker_compose": true,
    "helm": true,
    "kubernetes": true,
    "terraform": true
  },
  "manifests": {
    "script": "/manifests/dummy/script.sh",
    "docker_compose": "/manifests/dummy/docker-compose.yaml",
    "helm": "/manifests/dummy/helm.yaml",
    "kubernetes": "/manifests/dummy/k8s-deployment.yaml",
    "terraform": "/manifests/dummy/main.tf"
  },
  "default_credentials": {
    "username": null,
    "password": null
  },
  "notes": [],
  "repository_status": null,
  "community_integrations": {
    "proxmox_ve": {
      "supported": true,
      "script_id": "2fauth",
      "url": "https://community-scripts.github.io/ProxmoxVE/scripts?id=2fauth"
    },
    "yunohost": {
      "supported": true,
      "repo_name": "2FAuth_ynh",
      "url": "https://github.com/YunoHost-Apps/2FAuth_ynh"
    }
  }
}
