{
  "name": "coolify",
  "slug": "coolify",
  "tagline": "A self-hosted platform for deploying apps and databases on your servers",
  "subtitle": "",
  "description": "Coolify is an open-source alternative to Heroku and Netlify designed for self-hosters. It provides an easy-to-use UI for deploying applications, databases, and static sites on your own infrastructure using Docker or Kubernetes.",
  "categories": [
    146
  ],
  "metadata": {
    "sponsored": false,
    "license": "Apache-2.0",
    "version": "v4.0.0-beta.460",
    "date_app_added": "2025-11-23",
    "date_last_released": "2025-12-31",
    "date_last_commit": "2026-01-01",
    "github_stars": 49036,
    "github_contributors": 414,
    "github_commits_this_year": 15,
    "github_issues_open": 586,
    "github_issues_closed_this_year": 0,
    "github_releases_this_year": 0
  },
  "resources": {
    "website": "https://coolify.io",
    "documentation": "https://github.com/coollabsio/coolify",
    "source_code": "https://github.com/coollabsio/coolify",
    "logo": "/icons/coolify.webp",
    "screenshot": "",
    "issues": "https://github.com/coollabsio/coolify/issues",
    "releases": "https://github.com/coollabsio/coolify/releases"
  },
  "features": [
    {
      "title": "Heroku Alternative",
      "description": "Deploy apps with the same ease as Heroku. No vendor lock-in"
    },
    {
      "title": "One",
      "description": "Launch applications, databases, and sites instantly. Simplified deployment process"
    },
    {
      "title": "Docker Support",
      "description": "Support for both container orchestration platforms. Choose your stack"
    },
    {
      "title": "Git Integration",
      "description": "Automatic deployments from GitHub, GitLab, and Bitbucket. CI/CD built-in"
    },
    {
      "title": "Database Management",
      "description": "Deploy and manage PostgreSQL, MySQL, MongoDB, and more. Complete stack solution"
    },
    {
      "title": "Self-Hosted",
      "description": "Run your own PaaS on any infrastructure. Full control, zero monthly fees"
    }
  ],
  "platform_support": {
    "desktop": {
      "linux": false,
      "windows": false,
      "macos": false
    },
    "mobile": {
      "android": false,
      "ios": false
    },
    "web_app": false,
    "browser_extension": false,
    "cli_only": false
  },
  "hosting_options": {
    "self_hosted": false,
    "managed_cloud": false,
    "saas": false
  },
  "interfaces": {
    "cli": false,
    "gui": false,
    "web_ui": false,
    "api": false,
    "tui": false
  },
  "deployment_methods": {
    "script": true,
    "docker": true,
    "docker_compose": true,
    "helm": true,
    "kubernetes": true,
    "terraform": true
  },
  "manifests": {},
  "default_credentials": {
    "username": null,
    "password": null
  },
  "notes": [],
  "repository_status": null,
  "community_integrations": {
    "proxmox_ve": {
      "supported": true,
      "script_id": "coolify",
      "url": "https://community-scripts.github.io/ProxmoxVE/scripts?id=coolify"
    },
    "truenas": {
      "supported": true,
      "app_name": "coolify",
      "url": "https://apps.truenas.com/catalog/coolify"
    }
  }
}
