{
  "name": "dokploy",
  "slug": "dokploy",
  "tagline": "A self-hosted deployment platform for running apps with Docker",
  "subtitle": "",
  "description": "Dokploy is a self-hosted platform for deploying applications using a modern web UI. It supports Docker-based deployments, databases, custom domains, SSL, and secrets, aiming to simplify app hosting for individuals and small teams.",
  "categories": [
    146
  ],
  "metadata": {
    "sponsored": false,
    "license": "NOASSERTION",
    "version": "v0.26.2",
    "date_app_added": "2025-11-23",
    "date_last_released": "2025-12-13",
    "date_last_commit": "2025-12-28",
    "github_stars": 28581,
    "github_contributors": 251,
    "github_commits_this_year": 2724,
    "github_issues_open": 0,
    "github_issues_closed_this_year": 0,
    "github_releases_this_year": 79
  },
  "resources": {
    "website": "https://dokploy.com/",
    "documentation": "https://github.com/Dokploy/dokploy",
    "source_code": "https://github.com/Dokploy/dokploy",
    "logo": "/icons/dokploy.webp",
    "screenshot": "",
    "issues": "https://github.com/Dokploy/dokploy/issues",
    "releases": "https://github.com/Dokploy/dokploy/releases",
    "logo_light": "/icons/dokploy-light.webp"
  },
  "features": [
    {
      "title": "Docker Support",
      "description": "Deploy applications from Git repositories with automatic builds and Docker containerization"
    },
    {
      "title": "Database Backup",
      "description": "Provision and manage PostgreSQL, MySQL, MongoDB, and Redis databases with backup automation"
    },
    {
      "title": "End-to-End Encryption",
      "description": "Secure management of application secrets and environment variables with encryption"
    },
    {
      "title": "Analytics Dashboard",
      "description": "Real-time application monitoring with logs, metrics, and health status visualization"
    },
    {
      "title": "Load Balancing",
      "description": "Built-in load balancer with health checks and automatic failover for high availability"
    },
    {
      "title": "Backup System",
      "description": "Automated database and application backups with configurable retention policies"
    }
  ],
  "platform_support": {
    "desktop": {
      "linux": false,
      "windows": false,
      "macos": false
    },
    "mobile": {
      "android": false,
      "ios": false
    },
    "web_app": false,
    "browser_extension": false,
    "cli_only": false
  },
  "hosting_options": {
    "self_hosted": false,
    "managed_cloud": false,
    "saas": false
  },
  "interfaces": {
    "cli": false,
    "gui": false,
    "web_ui": false,
    "api": false,
    "tui": false
  },
  "deployment_methods": {
    "script": true,
    "docker": true,
    "docker_compose": true,
    "helm": true,
    "kubernetes": true,
    "terraform": true
  },
  "manifests": {},
  "default_credentials": {
    "username": null,
    "password": null
  },
  "notes": [],
  "repository_status": null,
  "community_integrations": {
    "proxmox_ve": {
      "supported": true,
      "script_id": "dokploy",
      "url": "https://community-scripts.github.io/ProxmoxVE/scripts?id=dokploy"
    }
  }
}
