{
  "name": "dumbdo",
  "slug": "dumbdo",
  "tagline": null,
  "description": "DumbDo is a basic self-hosted to-do list app. It focuses on straightforward task management with lists, completion status, and a clutter-free interface designed for users who want local control over their task data.",
  "categories": [
    159
  ],
  "metadata": {
    "sponsored": false,
    "license": "GPL-3.0",
    "version": null,
    "date_app_added": "2025-11-23",
    "date_last_released": null,
    "date_last_commit": "2025-08-27",
    "github_stars": 148
  },
  "resources": {
    "website": "https://github.com/DumbWareio/DumbDo",
    "documentation": "https://github.com/DumbWareio/DumbDo",
    "source_code": "https://github.com/DumbWareio/DumbDo",
    "logo": "/icons/dumbdo.webp",
    "issues": "https://github.com/DumbWareio/DumbDo/issues",
    "releases": null
  },
  "features": [
    "Task lists: Create multiple lists to organize tasks by project, context, or priority for structured workflow.",
    "Completion tracking: Mark tasks as done and view completion history to monitor productivity over time.",
    "Simple interface: Focus on task management without distractions from unnecessary features or complex navigation.",
    "Local data storage: Keep all task information on your own server for privacy and control over personal data.",
    "Quick entry: Add new tasks rapidly with minimal clicks to capture ideas and action items as they arise.",
    "List management: Rename, delete, or reorder lists to adapt your organization system as needs change.",
    "Mobile responsive: Access and update tasks from any device with a browser that adapts to screen size.",
    "No dependencies: Run with minimal server requirements and no external services for straightforward deployment."
  ],
  "platform_support": {
    "desktop": {
      "linux": false,
      "windows": false,
      "macos": false
    },
    "mobile": {
      "android": false,
      "ios": false
    },
    "web_app": false,
    "browser_extension": false,
    "cli_only": false
  },
  "hosting_options": {
    "self_hosted": false,
    "managed_cloud": false,
    "saas": false
  },
  "interfaces": {
    "cli": false,
    "gui": false,
    "web_ui": false,
    "api": false,
    "tui": false
  },
  "deployment_methods": {
    "script": true,
    "docker": true,
    "docker_compose": true,
    "helm": true,
    "kubernetes": true,
    "terraform": true
  },
  "manifests": {},
  "default_credentials": {
    "username": null,
    "password": null
  },
  "notes": [],
  "repository_status": null
}
