{
  "name": "forms-md",
  "slug": "forms-md",
  "tagline": "",
  "description": "FormsMD is a self-hosted Markdown-based form builder. It turns MD-like syntax into shareable forms with submissions tracked via a lightweight backend, making it ideal for simple surveys or feedback collection without external dependencies.",
  "categories": [
    157
  ],
  "metadata": {
    "sponsored": false,
    "license": "Apache-2.0",
    "version": null,
    "date_app_added": "2025-11-23",
    "date_last_released": null,
    "date_last_commit": "2025-04-27",
    "github_stars": 721
  },
  "resources": {
    "website": "https://forms.md",
    "documentation": "https://forms.md",
    "source_code": "https://github.com/formsmd/formsmd",
    "logo": "/icons/forms-md.webp",
    "issues": "https://github.com/formsmd/formsmd/issues",
    "releases": null
  },
  "features": [
    "Forms: Markdown-based form builder, Simple syntax, Submission tracking. Easy survey creation.",
    "Lightweight: Minimal dependencies. Fast deployment.",
    "Self-Hosted: No external services. Complete privacy.",
    "Feedback Collection: Perfect for simple surveys. Quick setup.",
    "Markdown Syntax: Write forms in plain text. Developer-friendly.",
    "Submission Management: View and export responses. Data control.",
    "Email Notifications: Get alerted of submissions. Stay informed.",
    "Custom Styling: Personalize form appearance. Your brand.",
    "API Access: Integrate with tools. Automation-ready."
  ],
  "platform_support": {
    "desktop": {
      "linux": false,
      "windows": false,
      "macos": false
    },
    "mobile": {
      "android": false,
      "ios": false
    },
    "web_app": false,
    "browser_extension": false,
    "cli_only": false
  },
  "hosting_options": {
    "self_hosted": false,
    "managed_cloud": false,
    "saas": false
  },
  "interfaces": {
    "cli": false,
    "gui": false,
    "web_ui": false,
    "api": false,
    "tui": false
  },
  "deployment_methods": {
    "script": false,
    "docker": false,
    "docker_compose": false,
    "helm": false,
    "kubernetes": false,
    "terraform": false
  },
  "manifests": {},
  "default_credentials": {
    "username": null,
    "password": null
  },
  "notes": [],
  "repository_status": null
}
