{
  "name": "imagor-studio",
  "slug": "imagor-studio",
  "tagline": null,
  "description": "Imagor Studio is a web interface for Imagor, an image processing server. It lets users compose and test transformations like resize, crop and filters visually, then generate the corresponding URLs for automated use.",
  "categories": [
    120
  ],
  "metadata": {
    "sponsored": false,
    "license": "MIT",
    "version": "v0.8.16",
    "date_app_added": "2025-11-23",
    "date_last_released": "2025-12-02",
    "date_last_commit": "2025-12-03",
    "github_stars": 150
  },
  "resources": {
    "website": "https://imagor.net",
    "documentation": "https://github.com/cshum/imagor-studio",
    "source_code": "https://github.com/cshum/imagor-studio",
    "logo": "/icons/imagor-studio.webp",
    "issues": "https://github.com/cshum/imagor-studio/issues",
    "releases": "https://github.com/cshum/imagor-studio/releases"
  },
  "features": [
    "Visual Editor: Compose image transformations visually without writing code.",
    "Real-Time Preview: See transformation results instantly as you adjust parameters.",
    "URL Generation: Generate Imagor-compatible URLs for automated image processing.",
    "Transformation Library: Access resize, crop, blur, rotate, and filter operations.",
    "Parameter Testing: Test different transformation combinations before deployment.",
    "Imagor Integration: Seamlessly works with Imagor image processing server.",
    "Batch Operations: Design transformations that can be applied to multiple images.",
    "Developer Tool: Bridge between visual design and programmatic image processing."
  ],
  "platform_support": {
    "desktop": {
      "linux": false,
      "windows": false,
      "macos": false
    },
    "mobile": {
      "android": false,
      "ios": false
    },
    "web_app": false,
    "browser_extension": false,
    "cli_only": false
  },
  "hosting_options": {
    "self_hosted": false,
    "managed_cloud": false,
    "saas": false
  },
  "interfaces": {
    "cli": false,
    "gui": false,
    "web_ui": false,
    "api": false,
    "tui": false
  },
  "deployment_methods": {
    "script": true,
    "docker": true,
    "docker_compose": true,
    "helm": true,
    "kubernetes": true,
    "terraform": true
  },
  "manifests": {},
  "default_credentials": {
    "username": null,
    "password": null
  },
  "notes": [],
  "repository_status": null
}
