{
  "name": "livebook",
  "slug": "livebook",
  "tagline": null,
  "description": "Livebook is a self-hosted notebook application for running Elixir code, visualizing data, and creating interactive workflows. It includes collaboration features and integrates with machine learning tools and runtimes.",
  "categories": [
    196
  ],
  "metadata": {
    "sponsored": false,
    "license": "Apache-2.0",
    "version": "v0.18.1",
    "date_app_added": "2025-11-23",
    "date_last_released": "2025-12-07",
    "date_last_commit": "2025-12-07",
    "github_stars": 5635
  },
  "resources": {
    "website": "https://livebook.dev",
    "documentation": "https://github.com/livebook-dev/livebook",
    "source_code": "https://github.com/livebook-dev/livebook",
    "logo": "/icons/livebook.webp",
    "issues": "https://github.com/livebook-dev/livebook/issues",
    "releases": "https://github.com/livebook-dev/livebook/releases"
  },
  "features": [
    "Interactive Notebooks: Elixir code execution, Data visualization, Live collaboration. Jupyter for Elixir.",
    "Machine Learning: ML integrations, Data processing, Model training. Build ML workflows in Elixir.",
    "Real-Time Collaboration: Multi-user editing, Shared sessions, Team workflows. Work together on notebooks.",
    "Self-Hosted: Run locally, Custom deployment, Full control. Own your notebook environment."
  ],
  "platform_support": {
    "desktop": {
      "linux": false,
      "windows": true,
      "macos": true
    },
    "mobile": {
      "android": false,
      "ios": false
    },
    "web_app": false,
    "browser_extension": false,
    "cli_only": false
  },
  "hosting_options": {
    "self_hosted": false,
    "managed_cloud": false,
    "saas": false
  },
  "interfaces": {
    "cli": false,
    "gui": false,
    "web_ui": false,
    "api": false,
    "tui": false
  },
  "deployment_methods": {
    "script": true,
    "docker": true,
    "docker_compose": true,
    "helm": true,
    "kubernetes": true,
    "terraform": true
  },
  "manifests": {},
  "default_credentials": {
    "username": null,
    "password": null
  },
  "notes": [],
  "repository_status": null
}
