{
  "name": "lunar",
  "slug": "lunar",
  "categories": [
    51
  ],
  "sponsored": false,
  "sponsored_expired": null,
  "date_created": "2025-11-23",
  "interface_port": null,
  "documentation": "github.com/lunarphp/lunar",
  "website": "lunarphp.com",
  "source_code": "github.com/lunarphp/lunar",
  "github_stars": "3352",
  "logo": "/icons/lunar.webp",
  "description": "Lunar is a headless eCommerce platform for Laravel developers. It offers advanced catalog management, custom product types, carts, checkout APIs, and a customizable admin interface for complete flexibility.",
  "tagline": null,
  "features": [
    "Headless Commerce: API-first architecture, Custom frontends, Flexible integration. Build any shopping experience.",
    "Product Management: Custom product types, Variant support, Inventory tracking. Manage complex product catalogs.",
    "Cart & Checkout: Shopping cart APIs, Checkout workflows, Payment integration. Complete eCommerce functionality.",
    "Order Management: Order processing, Fulfillment tracking, Customer orders. Handle the entire order lifecycle.",
    "Pricing Engine: Dynamic pricing, Customer groups, Promotional pricing. Flexible pricing strategies.",
    "Admin Interface: Customizable dashboard, Product management, Order processing. Manage your store efficiently.",
    "Laravel Integration: Native Laravel package, Eloquent models, Blade components. Built for Laravel developers.",
    "Extensible: Plugin system, Custom fields, Event hooks. Extend functionality to match your needs."
  ],
  "install_methods": [
    {
      "platform": {
        "desktop": {
          "linux": false,
          "windows": false,
          "macos": false
        },
        "mobile": {
          "android": false,
          "ios": false
        },
        "web_app": false,
        "browser_extension": false
      },
      "hosting": {
        "self_hosted": false,
        "saas": false,
        "managed_cloud": false
      },
      "ui": {
        "cli": false,
        "gui": false,
        "web_ui": false,
        "api": false,
        "tui": false
      },
      "deployment": {
        "script": true,
        "docker": true,
        "docker_compose": true,
        "helm": true,
        "kubernetes": true,
        "terraform": true
      }
    }
  ],
  "default_credentials": {
    "username": null,
    "password": null
  },
  "notes": [],
  "platform": {
    "desktop": false,
    "mobile": false,
    "web_extensions": false,
    "hosting": false,
    "ui_interface": false
  },
  "deployment": {
    "script": true,
    "docker": true,
    "docker_compose": true,
    "helm": true,
    "kubernetes": true,
    "terraform": true,
    "paths": {
      "script": "/public/manifest/dummy/script.sh",
      "docker": "/public/manifest/dummy/Dockerfile",
      "docker_compose": "/public/manifest/dummy/docker-compose.yaml",
      "helm": "/public/manifest/dummy/helm.yaml",
      "kubernetes": "/public/manifest/dummy/k8s-deployment.yaml",
      "terraform": "/public/manifest/dummy/main.tf"
    }
  }
}
