{
  "name": "plex-prerolls",
  "slug": "plex-prerolls",
  "tagline": null,
  "description": "Plex Prerolls is a self-hosted tool to manage and randomize video clips as prerolls in Plex Media Server. It includes custom rules and scheduling through a simple UI.",
  "categories": [
    100
  ],
  "metadata": {
    "sponsored": false,
    "license": "GPL-3.0",
    "version": "4.2.0",
    "date_app_added": "2025-11-23",
    "date_last_released": "2025-06-18",
    "date_last_commit": "2025-06-18",
    "github_stars": 83,
    "github_contributors": 3,
    "github_commits_this_year": 10,
    "github_issues_open": 0,
    "github_issues_closed_this_year": 0,
    "github_releases_this_year": 6
  },
  "resources": {
    "website": "https://github.com/nwithan8/plex-prerolls",
    "documentation": "https://github.com/nwithan8/plex-prerolls",
    "source_code": "https://github.com/nwithan8/plex-prerolls",
    "logo": "/icons/plex-prerolls.webp",
    "issues": "https://github.com/nwithan8/plex-prerolls/issues",
    "releases": "https://github.com/nwithan8/plex-prerolls/releases"
  },
  "features": [
    {
      "title": "Preroll Management",
      "description": "Organize and manage video clips to play before movies in Plex"
    },
    {
      "title": "Randomization",
      "description": "Randomly select prerolls from your collection for variety in each viewing"
    },
    {
      "title": "Scheduling Rules",
      "description": "Configure prerolls to play based on date, season, or custom schedules"
    },
    {
      "title": "Theme Customization",
      "description": "Create separate preroll collections for different occasions or themes"
    },
    {
      "title": "Plex Integration",
      "description": "Automatically update Plex server configuration with selected prerolls"
    },
    {
      "title": "Web Interface",
      "description": "Manage prerolls through an intuitive web-based control panel"
    },
    {
      "title": "Preview Playback",
      "description": "Preview preroll videos before adding them to rotation"
    },
    {
      "title": "Weight Settings",
      "description": "Assign probability weights to prerolls for more or less frequent playback"
    }
  ],
  "platform_support": {
    "desktop": {
      "linux": false,
      "windows": false,
      "macos": false
    },
    "mobile": {
      "android": false,
      "ios": false
    },
    "web_app": false,
    "browser_extension": false,
    "cli_only": false
  },
  "hosting_options": {
    "self_hosted": false,
    "managed_cloud": false,
    "saas": false
  },
  "interfaces": {
    "cli": false,
    "gui": false,
    "web_ui": false,
    "api": false,
    "tui": false
  },
  "deployment_methods": {
    "script": true,
    "docker": true,
    "docker_compose": true,
    "helm": true,
    "kubernetes": true,
    "terraform": true
  },
  "manifests": {},
  "default_credentials": {
    "username": null,
    "password": null
  },
  "notes": [],
  "repository_status": null,
  "community_integrations": {
    "proxmox_ve": {
      "supported": true,
      "script_id": "plex",
      "url": "https://community-scripts.github.io/ProxmoxVE/scripts?id=plex"
    }
  }
}
