{
  "name": "recommendarr",
  "slug": "recommendarr",
  "tagline": null,
  "description": "Recommendarr is a self-hosted tool that recommends movies and shows from your media library based on ratings and usage. It integrates with Plex, Radarr, and Sonarr.",
  "categories": [
    166
  ],
  "metadata": {
    "sponsored": false,
    "license": "MIT",
    "version": "1.4.4",
    "date_app_added": "2025-11-23",
    "date_last_released": "2025-04-13",
    "date_last_commit": "2025-04-14",
    "github_stars": 981
  },
  "resources": {
    "website": "https://github.com/fingerthief/recommendarr",
    "documentation": "https://github.com/fingerthief/recommendarr",
    "source_code": "https://github.com/fingerthief/recommendarr",
    "logo": "/icons/recommendarr.webp",
    "issues": "https://github.com/fingerthief/recommendarr/issues",
    "releases": "https://github.com/fingerthief/recommendarr/releases"
  },
  "features": [
    "Smart recommendations: Suggest movies and shows based on viewing history and ratings from your Plex library.",
    "Plex integration: Analyze watch history and user ratings to understand preferences and patterns.",
    "Radarr/Sonarr sync: Automatically add recommended content to your download queue for acquisition.",
    "Collaborative filtering: Generate suggestions based on what similar users enjoyed in their libraries.",
    "Trending content: Discover popular movies and shows that match your taste preferences.",
    "Watchlist management: Save recommendations for later and track which suggestions you've already seen.",
    "Rating analysis: Use IMDb, TMDb, and Trakt ratings to filter and rank recommendations.",
    "Genre preferences: Fine-tune suggestions by specifying favorite genres or excluding unwanted categories.",
    "User profiles: Create separate recommendation profiles for different family members or viewing moods.",
    "Discovery dashboard: Browse recommended content with posters, descriptions, and rating information.",
    "Notification system: Get alerts when highly-rated content matching your preferences becomes available.",
    "API access: Build custom integrations or automate recommendation workflows using REST endpoints."
  ],
  "platform_support": {
    "desktop": {
      "linux": false,
      "windows": false,
      "macos": false
    },
    "mobile": {
      "android": false,
      "ios": false
    },
    "web_app": false,
    "browser_extension": false,
    "cli_only": false
  },
  "hosting_options": {
    "self_hosted": false,
    "managed_cloud": false,
    "saas": false
  },
  "interfaces": {
    "cli": false,
    "gui": false,
    "web_ui": false,
    "api": false,
    "tui": false
  },
  "deployment_methods": {
    "script": true,
    "docker": true,
    "docker_compose": true,
    "helm": true,
    "kubernetes": true,
    "terraform": true
  },
  "manifests": {},
  "default_credentials": {
    "username": null,
    "password": null
  },
  "notes": [],
  "repository_status": null
}
