{
  "name": "vito",
  "slug": "vito",
  "tagline": "A deployment and release dashboard for managing environments and services",
  "subtitle": "",
  "description": "Vito is a self-hosted deployment and release dashboard for web services. It organizes environments, releases, and health checks into a unified web interface for teams.",
  "categories": [
    30
  ],
  "metadata": {
    "sponsored": false,
    "license": "AGPL-3.0",
    "version": "3.17.0",
    "date_app_added": "2025-11-23",
    "date_last_released": "2025-12-10",
    "date_last_commit": "2025-12-10",
    "github_stars": 2824,
    "github_contributors": 44,
    "github_commits_this_year": 403,
    "github_issues_open": 0,
    "github_issues_closed_this_year": 0,
    "github_releases_this_year": 45
  },
  "resources": {
    "website": "https://vitodeploy.com",
    "documentation": "https://github.com/vitodeploy/vito",
    "source_code": "https://github.com/vitodeploy/vito",
    "logo": "/icons/vito.webp",
    "screenshot": "",
    "issues": "https://github.com/vitodeploy/vito/issues",
    "releases": "https://github.com/vitodeploy/vito/releases",
    "logo_light": "/icons/vito-light.webp"
  },
  "features": [
    {
      "title": "Application Deployment",
      "description": "Deploy applications to servers",
      "core_feature": true
    },
    {
      "title": "Server Management",
      "description": "Manage connected servers",
      "core_feature": true
    },
    {
      "title": "Deployment Automation",
      "description": "Automate build and deployment steps",
      "core_feature": true
    },
    {
      "title": "Environment Variables",
      "description": "Configure environment settings"
    },
    {
      "title": "Deployment History",
      "description": "View past deployments"
    },
    {
      "title": "Self-Hosted Deployment",
      "description": "Run the deployment tool on your own infrastructure"
    }
  ],
  "platform_support": {
    "desktop": {
      "linux": false,
      "windows": false,
      "macos": false
    },
    "mobile": {
      "android": false,
      "ios": false
    },
    "web_app": false,
    "browser_extension": false,
    "cli_only": false
  },
  "hosting_options": {
    "self_hosted": false,
    "managed_cloud": false,
    "saas": false
  },
  "interfaces": {
    "cli": false,
    "gui": false,
    "web_ui": false,
    "api": false,
    "tui": false
  },
  "deployment_methods": {
    "script": true,
    "docker": true,
    "docker_compose": true,
    "helm": true,
    "kubernetes": true,
    "terraform": true
  },
  "manifests": {},
  "default_credentials": {
    "username": null,
    "password": null
  },
  "notes": [],
  "repository_status": null
}
